poetic_ontology_builder/__init__.py
poetic_ontology_builder/builder.py
poetic_ontology_builder/cli.py
poetic_ontology_builder/utils.py
poetic_ontology_builder-1.0.1.dist-info/METADATA
poetic_ontology_builder-1.0.1.dist-info/WHEEL
poetic_ontology_builder-1.0.1.dist-info/entry_points.txt
poetic_ontology_builder-1.0.1.dist-info/top_level.txt
poetic_ontology_builder-1.0.1.dist-info/RECORD
