Metadata-Version: 2.4
Name: poetic_ontology_builder
Version: 1.0.1
Summary: A tool for generating ontological knowledge graphs with emotional embeddings from text.
Home-page: https://huggingface.co/willt-dc/Rosa-V1
Author: Willinton Triana Cardona
Author-email: 
License: MIT
Project-URL: Homepage, https://huggingface.co/willt-dc/Rosa-V1
Project-URL: Repository, https://huggingface.co/willt-dc/Rosa-V1
Keywords: ontology,emotions,knowledge graph,AI,poetic computing
Requires-Python: >=3.8
Requires-Dist: transformers>=4.32.0
Requires-Dist: torch>=2.0.0
Requires-Dist: matplotlib
Requires-Dist: pyvis
Requires-Dist: owlready2
Requires-Dist: python-dotenv
Requires-Dist: google-generativeai
Dynamic: home-page
Dynamic: requires-python
